{"hfjqpnUc3zTQfbYTQVdEbA==":"s-l500-500x500.jpg","zJi0FEzw5b+zEQiNZGlmUA==":"background1.jpeg","00zZUyXhpQoaC0uKo25qvA==":"product1.jpg","mIIbxW0r7dEZSbMPwcoYdg==":"background2.jpg","pVFvCi8K/OFjiK/lzAzr6g==":"s-l500-1-500x500.jpg","OlFZKysi+x8RUNSGtgkAcA==":"s-l500%20(2)-496x500.jpg","NN2nkIr+OlFT5sRcFtKtBw==":"links-500x280.jpg","Up6QC+dLk4TnzmeGm8v8Fg==":"s-l1600%20(1)-1001x1001.jpg","elZn5eao8+OvyxxdDwt5hg==":"s-l1600%20(3)-1000x1000.jpg","NGwa8WhobPUtbBFMLe+o3g==":"s-l1600%20(2)-800x800.jpg","M+BOOxjoQ0YAu+3m4KdyrQ==":"mbr-1920x1285.jpg"}